datasphere_python/__init__.py
datasphere_python/client.py
datasphere_python/iam_generator.py
datasphere_python/jwt_generator.py
datasphere_python-0.0.3.dist-info/METADATA
datasphere_python-0.0.3.dist-info/WHEEL
datasphere_python-0.0.3.dist-info/top_level.txt
datasphere_python-0.0.3.dist-info/RECORD
